sequence_tagging/__init__.py
sequence_tagging/main.py
sequence_tagging/perceptron.py
sequence_tagging/preprocess_atis.py
sequence_tagging/process_data.py
sequence_tagging/tagger.py
sequence_tagging/data/model.p
sequence_tagging/data/tagdict.p
sequence_tagging-0.1.0.dist-info/DESCRIPTION.rst
sequence_tagging-0.1.0.dist-info/METADATA
sequence_tagging-0.1.0.dist-info/RECORD
sequence_tagging-0.1.0.dist-info/WHEEL
sequence_tagging-0.1.0.dist-info/metadata.json
sequence_tagging-0.1.0.dist-info/top_level.txt
