Metadata-Version: 2.0
Name: sequence-tagging
Version: 0.1.0
Summary: Sequence Tagging powered by the Averaged Perceptron.
Home-page: https://github.com/blester125/sequence_tagging
Author: Brian Lester
Author-email: blester125@gmail.com
License: MIT
Download-URL: https://github.com/blester125/sequence_tagging/archive/0.1.0.tar.gz
Keywords: NLP,sequence tagging,ML
Platform: UNKNOWN
